ipywatch/__init__.py
ipywatch/_modidx.py
ipywatch/history.py
ipywatch/ipywatch.py
ipywatch-0.0.3.dist-info/LICENSE
ipywatch-0.0.3.dist-info/METADATA
ipywatch-0.0.3.dist-info/WHEEL
ipywatch-0.0.3.dist-info/entry_points.txt
ipywatch-0.0.3.dist-info/top_level.txt
ipywatch-0.0.3.dist-info/RECORD
