Metadata-Version: 2.1
Name: ipywatch
Version: 0.0.3
Summary: A debugbar tool for ipywidgets/reacton/solara
Home-page: https://github.com/itepifanio/ipywatch
Author: Ítalo Epifânio
Author-email: italoepifaniols@gmail.com
License: Apache Software License 2.0
Keywords: nbdev jupyter notebook python
Classifier: Development Status :: 4 - Beta
Classifier: Intended Audience :: Developers
Classifier: Natural Language :: English
Classifier: Programming Language :: Python :: 3.9
Classifier: Programming Language :: Python :: 3.10
Classifier: Programming Language :: Python :: 3.11
Classifier: License :: OSI Approved :: Apache Software License
Requires-Python: >=3.9
License-File: LICENSE
Requires-Dist: ipykernel >=6.20.1
Provides-Extra: dev
Requires-Dist: solara >=1.26.1 ; extra == 'dev'
